example_gitlab_python_project/__init__.py
example_gitlab_python_project/example_gitlab_python_project.py
example_gitlab_python_project-0.1.0.dist-info/AUTHORS.rst
example_gitlab_python_project-0.1.0.dist-info/LICENSE
example_gitlab_python_project-0.1.0.dist-info/METADATA
example_gitlab_python_project-0.1.0.dist-info/WHEEL
example_gitlab_python_project-0.1.0.dist-info/top_level.txt
example_gitlab_python_project-0.1.0.dist-info/RECORD
